docs
python_files_merger
test
